MANIFEST.in
setup.py
bin/hw
hackwrench/__init__.py
hackwrench/bg.jpg
hackwrench/bg2.jpg
hackwrench/bg3.jpg
hackwrench/browser.py
hackwrench/browser.ui
hackwrench/browser_fixed.ui
hackwrench/common.js
hackwrench/conf.py
hackwrench/db.py
hackwrench/ext.py
hackwrench/favorite0.png
hackwrench/favorite1.png
hackwrench/gui.py
hackwrench/hackwrench.png
hackwrench/home.js
hackwrench/icon_close.png
hackwrench/icon_close_tab.png
hackwrench/icon_maximize.png
hackwrench/icon_minimize.png
hackwrench/icon_restore.png
hackwrench/inspector.py
hackwrench/plugins.py
hackwrench/session.py
hackwrench/sq.py
hackwrench/status.py
hackwrench/webkit_evaljs.py
hackwrench.egg-info/PKG-INFO
hackwrench.egg-info/SOURCES.txt
hackwrench.egg-info/dependency_links.txt
hackwrench.egg-info/top_level.txt
hackwrench/extensions/__init__.py
hackwrench/extensions/download.py
hackwrench/extensions/greasemonkey.py
hackwrench/extensions/open_all_links.py
hackwrench/nprefs/__init__.py