Metadata-Version: 1.0
Name: hackwrench
Version: 0.2
Summary: web browser based on python-webkitgtk
Home-page: http://tabed.org/software/hackwrench/
Author: Mikhail Sakhno
Author-email: pawn13@gmail.com
License: UNKNOWN
Platform: UNKNOWN
Classifier: Environment :: X11 Applications
Classifier: Intended Audience :: End Users/Desktop
Classifier: Programming Language :: Python
